Workbook

Sheet Executive Summary
B2: Financial Performance Analysis — FY2025 | the parent holding group
B3: Prepared by the Corporate Finance & Analytics Team — the parent holding group
B5: Key Metric | C5: Value
B6: Total Revenue | C6: ='P&L Statement'!N4
B7: Gross Profit | C7: ='P&L Statement'!N7
B8: Gross Margin % | C8: ='P&L Statement'!N7/'P&L Statement'!N4
B9: Operating Income (EBIT) | C9: ='P&L Statement'!N12
B10: Operating Margin % | C10: ='P&L Statement'!N12/'P&L Statement'!N4
B11: Net Income | C11: ='P&L Statement'!N15
B12: Net Margin % | C12: ='P&L Statement'!N15/'P&L Statement'!N4
B14: Key Findings
B15: 1. Revenue grew steadily across all quarters, with Q4 the strongest period.
B16: 2. Gross margin held above 55%, indicating healthy pricing and cost control.
B17: 3. Operating expenses grew slower than revenue, expanding operating margin.
B18: 4. Net income margin improved year-over-year due to disciplined opex management.
B19: 5. Marketing spend as a % of revenue increased, supporting the sales growth seen in Q3-Q4.

Sheet P&L Statement
A1: Line Item | B1: Jan | C1: Feb | D1: Mar | E1: Apr | F1: May | G1: Jun | H1: Jul | I1: Aug | J1: Sep | K1: Oct | L1: Nov | M1: Dec | N1: FY2025 Total
A2: Revenue | B2: 310000 | C2: 295000 | D2: 330000 | E2: 340000 | F2: 355000 | G2: 370000 | H2: 360000 | I2: 375000 | J2: 400000 | K2: 430000 | L2: 510000 | M2: 560000 | N2: =SUM(B2:M2)
A3: COGS | B3: =B2*0.43 | C3: =C2*0.43 | D3: =D2*0.43 | E3: =E2*0.43 | F3: =F2*0.43 | G3: =G2*0.43 | H3: =H2*0.43 | I3: =I2*0.43 | ... M3: =M2*0.43 | N3: =SUM(B3:M3)
A4: Net Revenue | B4: =B2 | C4: =C2 | D4: =D2 | E4: =E2 | F4: =F2 | G4: =G2 | H4: =H2 | I4: =I2 | ... N4: =N2
A5: Gross Profit | B5: =B2-B3 | C5: =C2-C3 | D5: =D2-D3 | E5: =E2-E3 | F5: =F2-F3 | G5: =G2-G3 | H5: =H2-H3 | I5: =I2-I3 | ... M5: =M2-M3 | N5: =SUM(B5:M5)
A6: Operating Expenses:
A7: Salaries & Benefits | B7: 85000 | C7: 85000 | D7: 85000 | E7: 85000 | F7: 85000 | G7: 85000 | H7: 85000 | I7: 85000 | J7: 85000 | K7: 85000 | L7: 85000 | M7: 85000 | N7: =SUM(B7:M7)
A8: Marketing | B8: 22000 | C8: 21000 | D8: 23000 | E8: 24000 | F8: 25000 | G8: 26000 | H8: 27000 | I8: 28000 | J8: 30000 | K8: 34000 | L8: 40000 | M8: 46000 | N8: =SUM(B8:M8)
A9: R&D | B9: 30000 | C9: 30000 | D9: 30000 | E9: 30000 | F9: 30000 | G9: 30000 | H9: 30000 | I9: 30000 | J9: 30000 | K9: 30000 | L9: 30000 | M9: 30000 | N9: =SUM(B9:M9)
A10: G&A | B10: 18000 | C10: 18000 | D10: 18000 | E10: 18000 | F10: 18000 | G10: 18000 | H10: 18000 | I10: 18000 | J10: 18000 | K10: 18000 | L10: 18000 | M10: 18000 | N10: =SUM(B10:M10)
A11: Total Operating Expenses | B11: =B7+B8+B9+B10 | C11: =C7+C8+C9+C10 | D11: =D7+D8+D9+D10 | E11: =E7+E8+E9+E10 | F11: =F7+F8+F9+F10 | G11: =G7+G8+G9+G10 | H11: =H7+H8+H9+H10 | I11: =I7+I8+I9+I10 | ... M11: =M7+M8+M9+M10 | N11: =SUM(B11:M11)
A12: Operating Income (EBIT) | B12: =B5-B11 | C12: =C5-C11 | D12: =D5-D11 | E12: =E5-E11 | F12: =F5-F11 | G12: =G5-G11 | H12: =H5-H11 | I12: =I5-I11 | ... M12: =M5-M11 | N12: =SUM(B12:M12)
A13: Income Tax (21%) | B13: =B12*0.21 | C13: =C12*0.21 | D13: =D12*0.21 | E13: =E12*0.21 | F13: =F12*0.21 | G13: =G12*0.21 | H13: =H12*0.21 | I13: =I12*0.21 | ... M13: =M12*0.21 | N13: =SUM(B13:M13)
A14: Net Income | B14: =B12-B13 | C14: =C12-C13 | D14: =D12-D13 | E14: =E12-E13 | F14: =F12-F13 | G14: =G12-G13 | H14: =H12-H13 | I14: =I12-I13 | ... M14: =M12-M13 | N14: =SUM(B14:M14)

Sheet Quarterly Summary
A1: Quarter | B1: Revenue | C1: Gross Profit | D1: Operating Income | E1: Net Income | F1: Net Margin %
A2: Q1 | B2: =SUM('P&L Statement'!B2:D2) | C2: =SUM('P&L Statement'!B5:D5) | D2: =SUM('P&L Statement'!B12:D12) | E2: =SUM('P&L Statement'!B14:D14) | F2: =E2/B2
A3: Q2 | B3: =SUM('P&L Statement'!E2:G2) | C3: =SUM('P&L Statement'!E5:G5) | D3: =SUM('P&L Statement'!E12:G12) | E3: =SUM('P&L Statement'!E14:G14) | F3: =E3/B3
A4: Q3 | B4: =SUM('P&L Statement'!H2:J2) | C4: =SUM('P&L Statement'!H5:J5) | D4: =SUM('P&L Statement'!H12:J12) | E4: =SUM('P&L Statement'!H14:J14) | F4: =E4/B4
A5: Q4 | B5: =SUM('P&L Statement'!K2:M2) | C5: =SUM('P&L Statement'!K5:M5) | D5: =SUM('P&L Statement'!K12:M12) | E5: =SUM('P&L Statement'!K14:M14) | F5: =E5/B5
