Workbook

Sheet Executive Summary
B2: Crop Yield & Farm Operations Analysis | a regional agribusiness operator
B3: Prepared by the Agronomy & Farm Operations Analytics Team — the parent holding group
B5: Key Metric | C5: Value
B6: Total Cultivated Area (ha) | C6: =SUM('Field Data'!E2:E25)
B7: Total Harvest Volume (tons) | C7: =SUM('Field Data'!H2:H25)
B8: Avg Yield (tons/ha) | C8: =C7/C6
B9: Total Production Cost | C9: =SUM('Field Data'!I2:I25)
B10: Total Revenue | C10: =SUM('Field Data'!J2:J25)
B11: Gross Margin | C11: =(C10-C9)/C10
B13: Key Findings
B14: 1. Maize and soybean fields deliver the highest yield per hectare among all crops grown this season.
B15: 2. Irrigated fields outperform rain-fed fields by a wide margin in both yield and revenue per hectare.
B16: 3. Fertilizer cost per hectare correlates positively with yield, but returns diminish beyond a certain threshold.
B17: 4. The Northern Plains region has the most productive soil conditions, followed by the River Valley region.
B18: 5. Wheat shows the lowest gross margin of the major crops, mainly due to high input cost relative to market price.

Sheet Field Data
A1: Field ID | B1: Region | C1: Crop | D1: Irrigation Type | E1: Area (ha) | F1: Seed Cost ($) | G1: Fertilizer Cost ($) | H1: Harvest Volume (tons) | I1: Production Cost ($) | J1: Revenue ($) | K1: Yield (tons/ha)
A2: F100 | B2: Southern Delta | C2: Sorghum | D2: Rain-fed | E2: 73.6 | F2: 9660 | G2: 13420 | H2: 174.4 | I2: 32010 | J2: 33010 | K2: =H2/E2
A3: F101 | B3: River Valley | C3: Maize | D3: Irrigated | E3: 25.6 | F3: 3420 | G3: 6600 | H3: 164.1 | I3: 16960 | J3: 33890 | K3: =H3/E3
A4: F102 | B4: Southern Delta | C4: Sorghum | D4: Rain-fed | E4: 61.7 | F4: 5170 | G4: 9630 | H4: 172.1 | I4: 27220 | J4: 33220 | K4: =H4/E4
A5: F103 | B5: Southern Delta | C5: Wheat | D5: Irrigated | E5: 78.2 | F5: 9260 | G5: 18370 | H5: 308.1 | I5: 38760 | J5: 79560 | K5: =H5/E5
A6: F104 | B6: Eastern Highlands | C6: Rice | D6: Rain-fed | E6: 89.7 | F6: 10990 | G6: 18260 | H6: 509.5 | I6: 61090 | J6: 157540 | K6: =H6/E6
A7: F105 | B7: Northern Plains | C7: Sorghum | D7: Rain-fed | E7: 45 | F7: 4640 | G7: 14080 | H7: 126.5 | I7: 19730 | J7: 22110 | K7: =H7/E7
A8: F106 | B8: River Valley | C8: Maize | D8: Irrigated | E8: 88.5 | F8: 7470 | G8: 22750 | H8: 539 | I8: 60730 | J8: 109020 | K8: =H8/E8
A9: F107 | B9: Northern Plains | C9: Wheat | D9: Irrigated | E9: 87.3 | F9: 7600 | G9: 16750 | H9: 372.8 | I9: 38560 | J9: 90100 | K9: =H9/E9
A10: F108 | B10: Southern Delta | C10: Soybean | D10: Rain-fed | E10: 29.1 | F10: 4050 | G10: 8170 | H10: 78.3 | I10: 14890 | J10: 33040 | K10: =H10/E10
A11: F109 | B11: Southern Delta | C11: Rice | D11: Rain-fed | E11: 15 | F11: 2080 | G11: 3760 | H11: 85.8 | I11: 11880 | J11: 25350 | K11: =H11/E11
A12: F110 | B12: River Valley | C12: Rice | D12: Rain-fed | E12: 60.2 | F12: 4970 | G12: 10530 | H12: 314.8 | I12: 42840 | J12: 92830 | K12: =H12/E12
A13: F111 | B13: Eastern Highlands | C13: Wheat | D13: Irrigated | E13: 20.6 | F13: 2430 | G13: 3140 | H13: 72.3 | I13: 9630 | J13: 19170 | K13: =H13/E13
... A25: F123 | B25: Northern Plains | C25: Wheat | D25: Rain-fed | E25: 51.1 | F25: 6230 | G25: 11980 | H25: 133.4 | I25: 25090 | J25: 37020 | K25: =H25/E25

Sheet Crop Summary
A1: Crop | B1: Total Area (ha) | C1: Total Harvest (tons) | D1: Avg Yield (tons/ha) | E1: Total Revenue ($) | F1: Total Cost ($) | G1: Gross Margin %
A2: Maize | B2: =SUMIF('Field Data'!C:C,A2,'Field Data'!E:E) | C2: =SUMIF('Field Data'!C:C,A2,'Field Data'!H:H) | D2: =C2/B2 | E2: =SUMIF('Field Data'!C:C,A2,'Field Data'!J:J) | F2: =SUMIF('Field Data'!C:C,A2,'Field Data'!I:I) | G2: =(E2-F2)/E2
A3: Soybean | B3: =SUMIF('Field Data'!C:C,A3,'Field Data'!E:E) | C3: =SUMIF('Field Data'!C:C,A3,'Field Data'!H:H) | D3: =C3/B3 | E3: =SUMIF('Field Data'!C:C,A3,'Field Data'!J:J) | F3: =SUMIF('Field Data'!C:C,A3,'Field Data'!I:I) | G3: =(E3-F3)/E3
A4: Wheat | B4: =SUMIF('Field Data'!C:C,A4,'Field Data'!E:E) | C4: =SUMIF('Field Data'!C:C,A4,'Field Data'!H:H) | D4: =C4/B4 | E4: =SUMIF('Field Data'!C:C,A4,'Field Data'!J:J) | F4: =SUMIF('Field Data'!C:C,A4,'Field Data'!I:I) | G4: =(E4-F4)/E4
A5: Rice | B5: =SUMIF('Field Data'!C:C,A5,'Field Data'!E:E) | C5: =SUMIF('Field Data'!C:C,A5,'Field Data'!H:H) | D5: =C5/B5 | E5: =SUMIF('Field Data'!C:C,A5,'Field Data'!J:J) | F5: =SUMIF('Field Data'!C:C,A5,'Field Data'!I:I) | G5: =(E5-F5)/E5
A6: Sorghum | B6: =SUMIF('Field Data'!C:C,A6,'Field Data'!E:E) | C6: =SUMIF('Field Data'!C:C,A6,'Field Data'!H:H) | D6: =C6/B6 | E6: =SUMIF('Field Data'!C:C,A6,'Field Data'!J:J) | F6: =SUMIF('Field Data'!C:C,A6,'Field Data'!I:I) | G6: =(E6-F6)/E6

Sheet Regional Summary
A1: Region | B1: Total Area (ha) | C1: Total Harvest (tons) | D1: Avg Yield (tons/ha) | E1: Total Revenue ($)
A2: Northern Plains | B2: =SUMIF('Field Data'!B:B,A2,'Field Data'!E:E) | C2: =SUMIF('Field Data'!B:B,A2,'Field Data'!H:H) | D2: =C2/B2 | E2: =SUMIF('Field Data'!B:B,A2,'Field Data'!J:J)
A3: River Valley | B3: =SUMIF('Field Data'!B:B,A3,'Field Data'!E:E) | C3: =SUMIF('Field Data'!B:B,A3,'Field Data'!H:H) | D3: =C3/B3 | E3: =SUMIF('Field Data'!B:B,A3,'Field Data'!J:J)
A4: Eastern Highlands | B4: =SUMIF('Field Data'!B:B,A4,'Field Data'!E:E) | C4: =SUMIF('Field Data'!B:B,A4,'Field Data'!H:H) | D4: =C4/B4 | E4: =SUMIF('Field Data'!B:B,A4,'Field Data'!J:J)
A5: Southern Delta | B5: =SUMIF('Field Data'!B:B,A5,'Field Data'!E:E) | C5: =SUMIF('Field Data'!B:B,A5,'Field Data'!H:H) | D5: =C5/B5 | E5: =SUMIF('Field Data'!B:B,A5,'Field Data'!J:J)
