Workbook

Sheet Executive Summary
B2: Livestock & Supply Chain Analysis | a regional agribusiness operator
B3: Prepared by the Supply Chain & Livestock Operations Team — the parent holding group
B5: Key Metric | C5: Value
B6: Total Herd/Flock Size | C6: =SUM('Livestock Data'!D2:D13)
B7: Total Output Volume | C7: =SUM('Livestock Data'!F2:F13)
B8: Total Feed Cost | C8: =SUM('Livestock Data'!G2:G13)
B9: Total Revenue | C9: =SUM('Livestock Data'!H2:H13)
B10: Avg Feed Conversion Cost | C10: =C8/C7
B11: Avg On-Time Delivery Rate | C11: =AVERAGE('Logistics Data'!F2:F13)
B13: Key Findings
B14: 1. Poultry operations generate the highest output volume relative to feed cost among all livestock types.
B15: 2. Dairy cattle show the strongest revenue per head, supported by stable year-round milk demand.
B16: 3. Cold-chain logistics routes to coastal distribution centers have the lowest on-time delivery rate, indicating a bottleneck.
B17: 4. Feed cost inflation has outpaced output growth for swine operations, compressing margins.
B18: 5. Consolidating shipments on the Northern route could reduce transport cost per ton based on current load factors.

Sheet Livestock Data
A1: Operation ID | B1: Livestock Type | C1: Farm Site | D1: Herd/Flock Size | E1: Avg Weight/Yield Unit | F1: Output Volume | G1: Feed Cost ($) | H1: Revenue ($)
A2: OP300 | B2: Swine | C2: Site B - River Valley | D2: 1392 | E2: 1.18 | F2: 362263 | G2: 362466 | H2: 791824
A3: OP301 | B3: Poultry (Broiler) | C3: Site A - Northern Plains | D3: 260 | E3: 0.9 | F3: 68825 | G3: 37245 | H3: 118042
A4: OP302 | B4: Poultry (Broiler) | C4: Site C - Eastern Highlands | D4: 1794 | E4: 0.86 | F4: 396766 | G4: 202504 | H4: 671852
A5: OP303 | B5: Beef Cattle | C5: Site A - Northern Plains | D5: 1010 | E5: 0.93 | F5: 185315 | G5: 212636 | H5: 541912
A6: OP304 | B6: Poultry (Layer) | C6: Site A - Northern Plains | D6: 2091 | E6: 1.06 | F6: 585128 | G6: 24260 | H6: 68933
A7: OP305 | B7: Swine | C7: Site B - River Valley | D7: 223 | E7: 0.97 | F7: 56249 | G7: 57678 | H7: 123767
A8: OP306 | B8: Dairy Cattle | C8: Site B - River Valley | D8: 1685 | E8: 1.03 | F8: 313652 | G8: 55390 | H8: 159298
A9: OP307 | B9: Beef Cattle | C9: Site A - Northern Plains | D9: 1623 | E9: 0.82 | F9: 251524 | G9: 264253 | H9: 844722
A10: OP308 | B10: Swine | C10: Site C - Eastern Highlands | D10: 680 | E10: 0.9 | F10: 136516 | G10: 125743 | H10: 267804
A11: OP309 | B11: Dairy Cattle | C11: Site C - Eastern Highlands | D11: 1266 | E11: 0.93 | F11: 220273 | G11: 43539 | H11: 109501
A12: OP310 | B12: Poultry (Broiler) | C12: Site B - River Valley | D12: 371 | E12: 1.09 | F12: 90329 | G12: 45458 | H12: 158597
A13: OP311 | B13: Poultry (Layer) | C13: Site A - Northern Plains | D13: 716 | E13: 0.96 | F13: 194131 | G13: 8479 | H13: 23716

Sheet Logistics Data
A1: Route | B1: Distribution Center | C1: Shipments | D1: Avg Transit Time (days) | E1: Transport Cost ($) | F1: On-Time Delivery Rate
A2: Northern Route | B2: Regional DC - North | C2: 140 | D2: 1.8 | E2: 30710 | F2: 0.972
A3: Southern Route | B3: Regional DC - South | C3: 213 | D3: 1.5 | E3: 24210 | F3: 0.948
A4: Coastal Route | B4: Coastal Distribution Center | C4: 177 | D4: 2.4 | E4: 36300 | F4: 0.661
A5: Eastern Route | B5: Regional DC - East | C5: 120 | D5: 1.2 | E5: 25200 | F5: 0.799
A6: Central Route | B6: Central Distribution Hub | C6: 119 | D6: 4.8 | E6: 20680 | F6: 0.861
A7: Western Route | B7: Regional DC - West | C7: 59 | D7: 3.4 | E7: 9340 | F7: 0.976

Sheet Livestock Summary
A1: Livestock Type | B1: Total Herd/Flock | C1: Total Output | D1: Total Feed Cost ($) | E1: Total Revenue ($) | F1: Margin %
A2: Dairy Cattle | B2: =SUMIF('Livestock Data'!B:B,A2,'Livestock Data'!D:D) | C2: =SUMIF('Livestock Data'!B:B,A2,'Livestock Data'!F:F) | D2: =SUMIF('Livestock Data'!B:B,A2,'Livestock Data'!G:G) | E2: =SUMIF('Livestock Data'!B:B,A2,'Livestock Data'!H:H) | F2: =IF(E2=0,0,(E2-D2)/E2)
A3: Beef Cattle | B3: =SUMIF('Livestock Data'!B:B,A3,'Livestock Data'!D:D) | C3: =SUMIF('Livestock Data'!B:B,A3,'Livestock Data'!F:F) | D3: =SUMIF('Livestock Data'!B:B,A3,'Livestock Data'!G:G) | E3: =SUMIF('Livestock Data'!B:B,A3,'Livestock Data'!H:H) | F3: =IF(E3=0,0,(E3-D3)/E3)
A4: Poultry (Broiler) | B4: =SUMIF('Livestock Data'!B:B,A4,'Livestock Data'!D:D) | C4: =SUMIF('Livestock Data'!B:B,A4,'Livestock Data'!F:F) | D4: =SUMIF('Livestock Data'!B:B,A4,'Livestock Data'!G:G) | E4: =SUMIF('Livestock Data'!B:B,A4,'Livestock Data'!H:H) | F4: =IF(E4=0,0,(E4-D4)/E4)
A5: Poultry (Layer) | B5: =SUMIF('Livestock Data'!B:B,A5,'Livestock Data'!D:D) | C5: =SUMIF('Livestock Data'!B:B,A5,'Livestock Data'!F:F) | D5: =SUMIF('Livestock Data'!B:B,A5,'Livestock Data'!G:G) | E5: =SUMIF('Livestock Data'!B:B,A5,'Livestock Data'!H:H) | F5: =IF(E5=0,0,(E5-D5)/E5)
A6: Swine | B6: =SUMIF('Livestock Data'!B:B,A6,'Livestock Data'!D:D) | C6: =SUMIF('Livestock Data'!B:B,A6,'Livestock Data'!F:F) | D6: =SUMIF('Livestock Data'!B:B,A6,'Livestock Data'!G:G) | E6: =SUMIF('Livestock Data'!B:B,A6,'Livestock Data'!H:H) | F6: =IF(E6=0,0,(E6-D6)/E6)
